<?xml version="1.0" encoding="UTF-8"?>
<!DOCTYPE ode SYSTEM "content.dtd">
<ode xmlns="http://www.intef.es/xsd/ode" version="2.0">
<userPreferences>
  <userPreference>
    <key>theme</key>
    <value>base</value>
  </userPreference>
</userPreferences>
<odeResources>
  <odeResource>
    <key>odeId</key>
    <value>20260423175554VCXXZS</value>
  </odeResource>
  <odeResource>
    <key>odeVersionId</key>
    <value>20260423175554ADIFM4</value>
  </odeResource>
  <odeResource>
    <key>exe_version</key>
    <value>3.0</value>
  </odeResource>
</odeResources>
<odeProperties>
  <odeProperty>
    <key>pp_title</key>
    <value>clase 9 de abril</value>
  </odeProperty>
  <odeProperty>
    <key>pp_author</key>
    <value>Angelica Magaly Bonilla</value>
  </odeProperty>
  <odeProperty>
    <key>pp_lang</key>
    <value>es</value>
  </odeProperty>
  <odeProperty>
    <key>pp_theme</key>
    <value>base</value>
  </odeProperty>
  <odeProperty>
    <key>pp_exelearning_version</key>
    <value>v4.0.0-rc2</value>
  </odeProperty>
  <odeProperty>
    <key>pp_modified</key>
    <value>1776983183086</value>
  </odeProperty>
  <odeProperty>
    <key>pp_addExeLink</key>
    <value>true</value>
  </odeProperty>
  <odeProperty>
    <key>pp_addPagination</key>
    <value>true</value>
  </odeProperty>
  <odeProperty>
    <key>pp_addSearchBox</key>
    <value>false</value>
  </odeProperty>
  <odeProperty>
    <key>pp_addAccessibilityToolbar</key>
    <value>false</value>
  </odeProperty>
  <odeProperty>
    <key>pp_addMathJax</key>
    <value>false</value>
  </odeProperty>
  <odeProperty>
    <key>exportSource</key>
    <value>true</value>
  </odeProperty>
  <odeProperty>
    <key>pp_globalFont</key>
    <value>default</value>
  </odeProperty>
</odeProperties>
<odeNavStructures>
<odeNavStructure>
  <odePageId>page-moc1wn8d-df66khprq</odePageId>
  <odeParentPageId></odeParentPageId>
  <pageName>Página nueva</pageName>
  <odeNavStructureOrder>0</odeNavStructureOrder>
  <odeNavStructureProperties>
    <odeNavStructureProperty>
      <key>titlePage</key>
      <value>Página nueva</value>
    </odeNavStructureProperty>
    <odeNavStructureProperty>
      <key>visibility</key>
      <value>true</value>
    </odeNavStructureProperty>
    <odeNavStructureProperty>
      <key>highlight</key>
      <value>false</value>
    </odeNavStructureProperty>
    <odeNavStructureProperty>
      <key>hidePageTitle</key>
      <value>false</value>
    </odeNavStructureProperty>
    <odeNavStructureProperty>
      <key>editableInPage</key>
      <value>false</value>
    </odeNavStructureProperty>
    <odeNavStructureProperty>
      <key>titlePage</key>
      <value>Página nueva</value>
    </odeNavStructureProperty>
    <odeNavStructureProperty>
      <key>titleNode</key>
      <value></value>
    </odeNavStructureProperty>
    <odeNavStructureProperty>
      <key>titleHtml</key>
      <value></value>
    </odeNavStructureProperty>
    <odeNavStructureProperty>
      <key>description</key>
      <value></value>
    </odeNavStructureProperty>
  </odeNavStructureProperties>
  <odePagStructures>
  </odePagStructures>
</odeNavStructure>
<odeNavStructure>
  <odePageId>page-moc1wn8f-dkkkxnpzw</odePageId>
  <odeParentPageId>page-moc1wn8d-df66khprq</odeParentPageId>
  <pageName>Actividades secuencia didáctica</pageName>
  <odeNavStructureOrder>0</odeNavStructureOrder>
  <odeNavStructureProperties>
    <odeNavStructureProperty>
      <key>titlePage</key>
      <value>Actividades secuencia didáctica</value>
    </odeNavStructureProperty>
    <odeNavStructureProperty>
      <key>visibility</key>
      <value>true</value>
    </odeNavStructureProperty>
    <odeNavStructureProperty>
      <key>highlight</key>
      <value>true</value>
    </odeNavStructureProperty>
    <odeNavStructureProperty>
      <key>hidePageTitle</key>
      <value>false</value>
    </odeNavStructureProperty>
    <odeNavStructureProperty>
      <key>editableInPage</key>
      <value>false</value>
    </odeNavStructureProperty>
    <odeNavStructureProperty>
      <key>titlePage</key>
      <value>Actividades secuencia didáctica</value>
    </odeNavStructureProperty>
    <odeNavStructureProperty>
      <key>titleNode</key>
      <value>Actividades secuencia didáctica</value>
    </odeNavStructureProperty>
    <odeNavStructureProperty>
      <key>titleHtml</key>
      <value></value>
    </odeNavStructureProperty>
    <odeNavStructureProperty>
      <key>description</key>
      <value></value>
    </odeNavStructureProperty>
  </odeNavStructureProperties>
  <odePagStructures>
    <odePagStructure>
      <odePageId>page-moc1wn8f-dkkkxnpzw</odePageId>
      <odeBlockId>20260423222439NDWJJI</odeBlockId>
      <blockName>Texto</blockName>
      <iconName></iconName>
      <odePagStructureOrder>1</odePagStructureOrder>
      <odePagStructureProperties>
        <odePagStructureProperty>
          <key>visibility</key>
          <value>true</value>
        </odePagStructureProperty>
        <odePagStructureProperty>
          <key>teacherOnly</key>
          <value>false</value>
        </odePagStructureProperty>
        <odePagStructureProperty>
          <key>allowToggle</key>
          <value>true</value>
        </odePagStructureProperty>
        <odePagStructureProperty>
          <key>minimized</key>
          <value>false</value>
        </odePagStructureProperty>
        <odePagStructureProperty>
          <key>cssClass</key>
          <value></value>
        </odePagStructureProperty>
      </odePagStructureProperties>
      <odeComponents>
        <odeComponent>
          <odePageId>page-moc1wn8f-dkkkxnpzw</odePageId>
          <odeBlockId>20260423222439NDWJJI</odeBlockId>
          <odeIdeviceId>202604162223479759WU</odeIdeviceId>
          <odeIdeviceTypeName>text</odeIdeviceTypeName>
          <htmlView><![CDATA[<div class="exe-text-template"><div class="textIdeviceContent">
            <div class="exe-text-activity">
                <div><p class="clearfix"></p></div>
            </div></div></div>]]></htmlView>
          <jsonProperties><![CDATA[{"ideviceId":"202604162223479759WU","textInfoDurationInput":"","textInfoDurationTextInput":"Duración","textInfoParticipantsInput":"","textInfoParticipantsTextInput":"Agrupamiento","textTextarea":"","textFeedbackInput":"Mostrar retroalimentación","textFeedbackTextarea":""}]]></jsonProperties>
          <odeComponentsOrder>1</odeComponentsOrder>
          <odeComponentsProperties>
            <odeComponentsProperty>
              <key>visibility</key>
              <value>true</value>
            </odeComponentsProperty>
            <odeComponentsProperty>
              <key>teacherOnly</key>
              <value>false</value>
            </odeComponentsProperty>
            <odeComponentsProperty>
              <key>cssClass</key>
              <value></value>
            </odeComponentsProperty>
          </odeComponentsProperties>
        </odeComponent>
      </odeComponents>
    </odePagStructure>
    <odePagStructure>
      <odePageId>page-moc1wn8f-dkkkxnpzw</odePageId>
      <odeBlockId>20260423222439NIOBUT</odeBlockId>
      <blockName>Texto</blockName>
      <iconName></iconName>
      <odePagStructureOrder>2</odePagStructureOrder>
      <odePagStructureProperties>
        <odePagStructureProperty>
          <key>visibility</key>
          <value>true</value>
        </odePagStructureProperty>
        <odePagStructureProperty>
          <key>teacherOnly</key>
          <value>false</value>
        </odePagStructureProperty>
        <odePagStructureProperty>
          <key>allowToggle</key>
          <value>true</value>
        </odePagStructureProperty>
        <odePagStructureProperty>
          <key>minimized</key>
          <value>false</value>
        </odePagStructureProperty>
        <odePagStructureProperty>
          <key>cssClass</key>
          <value></value>
        </odePagStructureProperty>
      </odePagStructureProperties>
      <odeComponents>
        <odeComponent>
          <odePageId>page-moc1wn8f-dkkkxnpzw</odePageId>
          <odeBlockId>20260423222439NIOBUT</odeBlockId>
          <odeIdeviceId>20260423161217791LE9</odeIdeviceId>
          <odeIdeviceTypeName>text</odeIdeviceTypeName>
          <htmlView><![CDATA[<div class="exe-text-template"><div class="textIdeviceContent">
            <div class="exe-text-activity">
                <div><p class="clearfix"></p></div>
            </div></div></div>]]></htmlView>
          <jsonProperties><![CDATA[{"ideviceId":"20260423161217791LE9","textInfoDurationInput":"","textInfoDurationTextInput":"Duración","textInfoParticipantsInput":"","textInfoParticipantsTextInput":"Agrupamiento","textTextarea":"","textFeedbackInput":"Mostrar retroalimentación","textFeedbackTextarea":""}]]></jsonProperties>
          <odeComponentsOrder>1</odeComponentsOrder>
          <odeComponentsProperties>
            <odeComponentsProperty>
              <key>visibility</key>
              <value>true</value>
            </odeComponentsProperty>
            <odeComponentsProperty>
              <key>teacherOnly</key>
              <value>false</value>
            </odeComponentsProperty>
            <odeComponentsProperty>
              <key>cssClass</key>
              <value></value>
            </odeComponentsProperty>
          </odeComponentsProperties>
        </odeComponent>
      </odeComponents>
    </odePagStructure>
  </odePagStructures>
</odeNavStructure>
<odeNavStructure>
  <odePageId>page-moc1wn8k-akfxndc0k</odePageId>
  <odeParentPageId>page-moc1wn8f-dkkkxnpzw</odeParentPageId>
  <pageName>Titulo del ova y presentación</pageName>
  <odeNavStructureOrder>0</odeNavStructureOrder>
  <odeNavStructureProperties>
    <odeNavStructureProperty>
      <key>titlePage</key>
      <value>Titulo del ova y presentación</value>
    </odeNavStructureProperty>
    <odeNavStructureProperty>
      <key>visibility</key>
      <value>true</value>
    </odeNavStructureProperty>
    <odeNavStructureProperty>
      <key>highlight</key>
      <value>false</value>
    </odeNavStructureProperty>
    <odeNavStructureProperty>
      <key>hidePageTitle</key>
      <value>false</value>
    </odeNavStructureProperty>
    <odeNavStructureProperty>
      <key>editableInPage</key>
      <value>false</value>
    </odeNavStructureProperty>
    <odeNavStructureProperty>
      <key>titlePage</key>
      <value>Titulo del ova y presentación</value>
    </odeNavStructureProperty>
    <odeNavStructureProperty>
      <key>titleNode</key>
      <value></value>
    </odeNavStructureProperty>
    <odeNavStructureProperty>
      <key>titleHtml</key>
      <value></value>
    </odeNavStructureProperty>
    <odeNavStructureProperty>
      <key>description</key>
      <value></value>
    </odeNavStructureProperty>
  </odeNavStructureProperties>
  <odePagStructures>
    <odePagStructure>
      <odePageId>page-moc1wn8k-akfxndc0k</odePageId>
      <odeBlockId>20260423222439SRSFJY</odeBlockId>
      <blockName>El ciclo del agua: comprendiendo su importancia en la naturaleza.</blockName>
      <iconName>icon_reflection</iconName>
      <odePagStructureOrder>1</odePagStructureOrder>
      <odePagStructureProperties>
        <odePagStructureProperty>
          <key>visibility</key>
          <value>true</value>
        </odePagStructureProperty>
        <odePagStructureProperty>
          <key>teacherOnly</key>
          <value>false</value>
        </odePagStructureProperty>
        <odePagStructureProperty>
          <key>allowToggle</key>
          <value>true</value>
        </odePagStructureProperty>
        <odePagStructureProperty>
          <key>minimized</key>
          <value>false</value>
        </odePagStructureProperty>
        <odePagStructureProperty>
          <key>cssClass</key>
          <value></value>
        </odePagStructureProperty>
      </odePagStructureProperties>
      <odeComponents>
        <odeComponent>
          <odePageId>page-moc1wn8k-akfxndc0k</odePageId>
          <odeBlockId>20260423222439SRSFJY</odeBlockId>
          <odeIdeviceId>20260412124748909SW9</odeIdeviceId>
          <odeIdeviceTypeName>text</odeIdeviceTypeName>
          <htmlView><![CDATA[<div class="exe-text-template"><div class="textIdeviceContent">
            <div class="exe-text-activity">
                <div><p><br></p>
<p>&nbsp; <img src="{{context_path}}/content/resources/20260412124748909SW9/mceclip0.png"></p><p class="clearfix"></p></div>
            </div></div></div>]]></htmlView>
          <jsonProperties><![CDATA[{"ideviceId":"20260412124748909SW9","textInfoDurationInput":"","textInfoDurationTextInput":"Duración","textInfoParticipantsInput":"","textInfoParticipantsTextInput":"Este Objeto Virtual está dirigido a estudiantes de grado tercero. Se presenta como una secuencia didáctica organizada que permite comprender el ciclo del agua mediante actividades activas, experimentación y reflexión sobre su importancia en la vida cotidiana.","textTextarea":"<p><br /></p>\n<p>  <img src=\"{{context_path}}/content/resources/20260412124748909SW9/mceclip0.png\" /></p>","textFeedbackInput":"Mostrar retroalimentación","textFeedbackTextarea":""}]]></jsonProperties>
          <odeComponentsOrder>1</odeComponentsOrder>
          <odeComponentsProperties>
            <odeComponentsProperty>
              <key>visibility</key>
              <value>true</value>
            </odeComponentsProperty>
            <odeComponentsProperty>
              <key>teacherOnly</key>
              <value>false</value>
            </odeComponentsProperty>
            <odeComponentsProperty>
              <key>cssClass</key>
              <value></value>
            </odeComponentsProperty>
          </odeComponentsProperties>
        </odeComponent>
      </odeComponents>
    </odePagStructure>
    <odePagStructure>
      <odePageId>page-moc1wn8k-akfxndc0k</odePageId>
      <odeBlockId>20260423222439AFXYMM</odeBlockId>
      <blockName>el viaje secreto del agua</blockName>
      <iconName></iconName>
      <odePagStructureOrder>2</odePagStructureOrder>
      <odePagStructureProperties>
        <odePagStructureProperty>
          <key>visibility</key>
          <value>true</value>
        </odePagStructureProperty>
        <odePagStructureProperty>
          <key>teacherOnly</key>
          <value>false</value>
        </odePagStructureProperty>
        <odePagStructureProperty>
          <key>allowToggle</key>
          <value>true</value>
        </odePagStructureProperty>
        <odePagStructureProperty>
          <key>minimized</key>
          <value>false</value>
        </odePagStructureProperty>
        <odePagStructureProperty>
          <key>cssClass</key>
          <value></value>
        </odePagStructureProperty>
      </odePagStructureProperties>
      <odeComponents>
        <odeComponent>
          <odePageId>page-moc1wn8k-akfxndc0k</odePageId>
          <odeBlockId>20260423222439AFXYMM</odeBlockId>
          <odeIdeviceId>20260412125810163J9C</odeIdeviceId>
          <odeIdeviceTypeName>text</odeIdeviceTypeName>
          <htmlView><![CDATA[<div class="exe-text-template"><div class="textIdeviceContent">
            <div class="exe-text-activity">
                <div><p>Este Objeto Virtual está dirigido a estudiantes de grado tercero. Se presenta como una secuencia didáctica organizada que permite comprender el ciclo del agua mediante actividades activas, experimentación y reflexión sobre su importancia en la vida cotidiana.</p><p class="clearfix"></p></div>
            </div></div></div>]]></htmlView>
          <jsonProperties><![CDATA[{"ideviceId":"20260412125810163J9C","textInfoDurationInput":"","textInfoDurationTextInput":"Duración","textInfoParticipantsInput":"","textInfoParticipantsTextInput":"Agrupamiento","textTextarea":"<p>Este Objeto Virtual está dirigido a estudiantes de grado tercero. Se presenta como una secuencia didáctica organizada que permite comprender el ciclo del agua mediante actividades activas, experimentación y reflexión sobre su importancia en la vida cotidiana.</p>","textFeedbackInput":"Mostrar retroalimentación","textFeedbackTextarea":""}]]></jsonProperties>
          <odeComponentsOrder>1</odeComponentsOrder>
          <odeComponentsProperties>
            <odeComponentsProperty>
              <key>visibility</key>
              <value>true</value>
            </odeComponentsProperty>
            <odeComponentsProperty>
              <key>teacherOnly</key>
              <value>false</value>
            </odeComponentsProperty>
            <odeComponentsProperty>
              <key>cssClass</key>
              <value></value>
            </odeComponentsProperty>
          </odeComponentsProperties>
        </odeComponent>
      </odeComponents>
    </odePagStructure>
  </odePagStructures>
</odeNavStructure>
<odeNavStructure>
  <odePageId>page-moc1wn8m-n2nvr3zif</odePageId>
  <odeParentPageId>page-moc1wn8f-dkkkxnpzw</odeParentPageId>
  <pageName>Objetivos.</pageName>
  <odeNavStructureOrder>1</odeNavStructureOrder>
  <odeNavStructureProperties>
    <odeNavStructureProperty>
      <key>titlePage</key>
      <value>Objetivos.</value>
    </odeNavStructureProperty>
    <odeNavStructureProperty>
      <key>visibility</key>
      <value>true</value>
    </odeNavStructureProperty>
    <odeNavStructureProperty>
      <key>highlight</key>
      <value>false</value>
    </odeNavStructureProperty>
    <odeNavStructureProperty>
      <key>hidePageTitle</key>
      <value>false</value>
    </odeNavStructureProperty>
    <odeNavStructureProperty>
      <key>editableInPage</key>
      <value>false</value>
    </odeNavStructureProperty>
    <odeNavStructureProperty>
      <key>titlePage</key>
      <value>Objetivos.</value>
    </odeNavStructureProperty>
    <odeNavStructureProperty>
      <key>titleNode</key>
      <value></value>
    </odeNavStructureProperty>
    <odeNavStructureProperty>
      <key>titleHtml</key>
      <value></value>
    </odeNavStructureProperty>
    <odeNavStructureProperty>
      <key>description</key>
      <value></value>
    </odeNavStructureProperty>
  </odeNavStructureProperties>
  <odePagStructures>
    <odePagStructure>
      <odePageId>page-moc1wn8m-n2nvr3zif</odePageId>
      <odeBlockId>20260423222439VXFHXS</odeBlockId>
      <blockName>OBJETIVOS</blockName>
      <iconName></iconName>
      <odePagStructureOrder>1</odePagStructureOrder>
      <odePagStructureProperties>
        <odePagStructureProperty>
          <key>visibility</key>
          <value>true</value>
        </odePagStructureProperty>
        <odePagStructureProperty>
          <key>teacherOnly</key>
          <value>false</value>
        </odePagStructureProperty>
        <odePagStructureProperty>
          <key>allowToggle</key>
          <value>true</value>
        </odePagStructureProperty>
        <odePagStructureProperty>
          <key>minimized</key>
          <value>false</value>
        </odePagStructureProperty>
        <odePagStructureProperty>
          <key>cssClass</key>
          <value></value>
        </odePagStructureProperty>
      </odePagStructureProperties>
      <odeComponents>
        <odeComponent>
          <odePageId>page-moc1wn8m-n2nvr3zif</odePageId>
          <odeBlockId>20260423222439VXFHXS</odeBlockId>
          <odeIdeviceId>20260409181134443D1E</odeIdeviceId>
          <odeIdeviceTypeName>text</odeIdeviceTypeName>
          <htmlView><![CDATA[<div class="exe-text-template"><div class="textIdeviceContent">
            <div class="exe-text-activity">
                <div><p>&nbsp; <img src="{{context_path}}/content/resources/20260409181134443D1E/mceclip1.png"></p><p class="clearfix"></p></div>
            </div></div></div>]]></htmlView>
          <jsonProperties><![CDATA[{"ideviceId":"20260409181134443D1E","textInfoDurationInput":"","textInfoDurationTextInput":"Duración","textInfoParticipantsInput":"","textInfoParticipantsTextInput":"Agrupamiento","textTextarea":"<p>  <img src=\"{{context_path}}/content/resources/20260409181134443D1E/mceclip1.png\" /></p>","textFeedbackInput":"Mostrar retroalimentación","textFeedbackTextarea":""}]]></jsonProperties>
          <odeComponentsOrder>1</odeComponentsOrder>
          <odeComponentsProperties>
            <odeComponentsProperty>
              <key>visibility</key>
              <value>true</value>
            </odeComponentsProperty>
            <odeComponentsProperty>
              <key>teacherOnly</key>
              <value>false</value>
            </odeComponentsProperty>
            <odeComponentsProperty>
              <key>cssClass</key>
              <value></value>
            </odeComponentsProperty>
          </odeComponentsProperties>
        </odeComponent>
      </odeComponents>
    </odePagStructure>
  </odePagStructures>
</odeNavStructure>
<odeNavStructure>
  <odePageId>page-moc1wn8n-ty8veupyr</odePageId>
  <odeParentPageId>page-moc1wn8f-dkkkxnpzw</odeParentPageId>
  <pageName>Fundamentación</pageName>
  <odeNavStructureOrder>2</odeNavStructureOrder>
  <odeNavStructureProperties>
    <odeNavStructureProperty>
      <key>titlePage</key>
      <value>Fundamentación</value>
    </odeNavStructureProperty>
    <odeNavStructureProperty>
      <key>visibility</key>
      <value>true</value>
    </odeNavStructureProperty>
    <odeNavStructureProperty>
      <key>highlight</key>
      <value>false</value>
    </odeNavStructureProperty>
    <odeNavStructureProperty>
      <key>hidePageTitle</key>
      <value>false</value>
    </odeNavStructureProperty>
    <odeNavStructureProperty>
      <key>editableInPage</key>
      <value>false</value>
    </odeNavStructureProperty>
    <odeNavStructureProperty>
      <key>titlePage</key>
      <value>Fundamentación</value>
    </odeNavStructureProperty>
    <odeNavStructureProperty>
      <key>titleNode</key>
      <value></value>
    </odeNavStructureProperty>
    <odeNavStructureProperty>
      <key>titleHtml</key>
      <value></value>
    </odeNavStructureProperty>
    <odeNavStructureProperty>
      <key>description</key>
      <value></value>
    </odeNavStructureProperty>
  </odeNavStructureProperties>
  <odePagStructures>
    <odePagStructure>
      <odePageId>page-moc1wn8n-ty8veupyr</odePageId>
      <odeBlockId>20260423222439OQNJRD</odeBlockId>
      <blockName>FUNDAMENTOS</blockName>
      <iconName></iconName>
      <odePagStructureOrder>1</odePagStructureOrder>
      <odePagStructureProperties>
        <odePagStructureProperty>
          <key>visibility</key>
          <value>true</value>
        </odePagStructureProperty>
        <odePagStructureProperty>
          <key>teacherOnly</key>
          <value>false</value>
        </odePagStructureProperty>
        <odePagStructureProperty>
          <key>allowToggle</key>
          <value>true</value>
        </odePagStructureProperty>
        <odePagStructureProperty>
          <key>minimized</key>
          <value>false</value>
        </odePagStructureProperty>
        <odePagStructureProperty>
          <key>cssClass</key>
          <value></value>
        </odePagStructureProperty>
      </odePagStructureProperties>
      <odeComponents>
      </odeComponents>
    </odePagStructure>
    <odePagStructure>
      <odePageId>page-moc1wn8n-ty8veupyr</odePageId>
      <odeBlockId>20260423222439EPRLSI</odeBlockId>
      <blockName>fundamentos pedagógicos.</blockName>
      <iconName></iconName>
      <odePagStructureOrder>2</odePagStructureOrder>
      <odePagStructureProperties>
        <odePagStructureProperty>
          <key>visibility</key>
          <value>true</value>
        </odePagStructureProperty>
        <odePagStructureProperty>
          <key>teacherOnly</key>
          <value>false</value>
        </odePagStructureProperty>
        <odePagStructureProperty>
          <key>allowToggle</key>
          <value>true</value>
        </odePagStructureProperty>
        <odePagStructureProperty>
          <key>minimized</key>
          <value>false</value>
        </odePagStructureProperty>
        <odePagStructureProperty>
          <key>cssClass</key>
          <value></value>
        </odePagStructureProperty>
      </odePagStructureProperties>
      <odeComponents>
        <odeComponent>
          <odePageId>page-moc1wn8n-ty8veupyr</odePageId>
          <odeBlockId>20260423222439EPRLSI</odeBlockId>
          <odeIdeviceId>20260416212900167MV6</odeIdeviceId>
          <odeIdeviceTypeName>download-source-file</odeIdeviceTypeName>
          <htmlView><![CDATA[<div class="exe-download-package-instructions"><p><img src="{{context_path}}/content/resources/20260416212900167MV6/mceclip3_1.png" /></p>
<p><br /></p>
<p><br /></p>
<p style="text-align: center;">Este contenido fue creado con <a href="http://exelearning.net/">eXeLearning</a>, el editor libre y de fuente abierta diseñado para crear recursos educativos.</p></div><p class="exe-download-package-link"><a download="exe-package:elp-name" href="exe-package:elp" style="background-color:#107375;color:#ffffff;">Descargar el archivo .elpx</a></p>]]></htmlView>
          <jsonProperties></jsonProperties>
          <odeComponentsOrder>1</odeComponentsOrder>
          <odeComponentsProperties>
            <odeComponentsProperty>
              <key>visibility</key>
              <value>true</value>
            </odeComponentsProperty>
            <odeComponentsProperty>
              <key>teacherOnly</key>
              <value>false</value>
            </odeComponentsProperty>
            <odeComponentsProperty>
              <key>cssClass</key>
              <value></value>
            </odeComponentsProperty>
          </odeComponentsProperties>
        </odeComponent>
      </odeComponents>
    </odePagStructure>
  </odePagStructures>
</odeNavStructure>
<odeNavStructure>
  <odePageId>page-moc1wn8o-9k9m8mtna</odePageId>
  <odeParentPageId>page-moc1wn8f-dkkkxnpzw</odeParentPageId>
  <pageName>Contenidos</pageName>
  <odeNavStructureOrder>3</odeNavStructureOrder>
  <odeNavStructureProperties>
    <odeNavStructureProperty>
      <key>titlePage</key>
      <value>Contenidos</value>
    </odeNavStructureProperty>
    <odeNavStructureProperty>
      <key>visibility</key>
      <value>true</value>
    </odeNavStructureProperty>
    <odeNavStructureProperty>
      <key>highlight</key>
      <value>false</value>
    </odeNavStructureProperty>
    <odeNavStructureProperty>
      <key>hidePageTitle</key>
      <value>false</value>
    </odeNavStructureProperty>
    <odeNavStructureProperty>
      <key>editableInPage</key>
      <value>false</value>
    </odeNavStructureProperty>
    <odeNavStructureProperty>
      <key>titlePage</key>
      <value>Contenidos</value>
    </odeNavStructureProperty>
    <odeNavStructureProperty>
      <key>titleNode</key>
      <value></value>
    </odeNavStructureProperty>
    <odeNavStructureProperty>
      <key>titleHtml</key>
      <value></value>
    </odeNavStructureProperty>
    <odeNavStructureProperty>
      <key>description</key>
      <value></value>
    </odeNavStructureProperty>
  </odeNavStructureProperties>
  <odePagStructures>
    <odePagStructure>
      <odePageId>page-moc1wn8o-9k9m8mtna</odePageId>
      <odeBlockId>20260423222439FJRZXG</odeBlockId>
      <blockName>CONTENIDOS</blockName>
      <iconName></iconName>
      <odePagStructureOrder>1</odePagStructureOrder>
      <odePagStructureProperties>
        <odePagStructureProperty>
          <key>visibility</key>
          <value>true</value>
        </odePagStructureProperty>
        <odePagStructureProperty>
          <key>teacherOnly</key>
          <value>false</value>
        </odePagStructureProperty>
        <odePagStructureProperty>
          <key>allowToggle</key>
          <value>true</value>
        </odePagStructureProperty>
        <odePagStructureProperty>
          <key>minimized</key>
          <value>false</value>
        </odePagStructureProperty>
        <odePagStructureProperty>
          <key>cssClass</key>
          <value></value>
        </odePagStructureProperty>
      </odePagStructureProperties>
      <odeComponents>
        <odeComponent>
          <odePageId>page-moc1wn8o-9k9m8mtna</odePageId>
          <odeBlockId>20260423222439FJRZXG</odeBlockId>
          <odeIdeviceId>20260416213442347ITR</odeIdeviceId>
          <odeIdeviceTypeName>text</odeIdeviceTypeName>
          <htmlView><![CDATA[<div class="exe-text-template"><div class="textIdeviceContent">
            <div class="exe-text-activity">
                <div><p><img src="{{context_path}}/content/resources/20260416213442347ITR/mceclip4.png"></p><p class="clearfix"></p></div>
            </div></div></div>]]></htmlView>
          <jsonProperties><![CDATA[{"ideviceId":"20260416213442347ITR","textInfoDurationInput":"","textInfoDurationTextInput":"Duración","textInfoParticipantsInput":"","textInfoParticipantsTextInput":"Agrupamiento","textTextarea":"<p><img src=\"{{context_path}}/content/resources/20260416213442347ITR/mceclip4.png\" /></p>","textFeedbackInput":"Mostrar retroalimentación","textFeedbackTextarea":""}]]></jsonProperties>
          <odeComponentsOrder>1</odeComponentsOrder>
          <odeComponentsProperties>
            <odeComponentsProperty>
              <key>visibility</key>
              <value>true</value>
            </odeComponentsProperty>
            <odeComponentsProperty>
              <key>teacherOnly</key>
              <value>false</value>
            </odeComponentsProperty>
            <odeComponentsProperty>
              <key>cssClass</key>
              <value></value>
            </odeComponentsProperty>
          </odeComponentsProperties>
        </odeComponent>
      </odeComponents>
    </odePagStructure>
  </odePagStructures>
</odeNavStructure>
<odeNavStructure>
  <odePageId>page-moc1wn8p-02z4ubxai</odePageId>
  <odeParentPageId>page-moc1wn8f-dkkkxnpzw</odeParentPageId>
  <pageName>Justificación</pageName>
  <odeNavStructureOrder>4</odeNavStructureOrder>
  <odeNavStructureProperties>
    <odeNavStructureProperty>
      <key>titlePage</key>
      <value>Justificación</value>
    </odeNavStructureProperty>
    <odeNavStructureProperty>
      <key>visibility</key>
      <value>true</value>
    </odeNavStructureProperty>
    <odeNavStructureProperty>
      <key>highlight</key>
      <value>false</value>
    </odeNavStructureProperty>
    <odeNavStructureProperty>
      <key>hidePageTitle</key>
      <value>false</value>
    </odeNavStructureProperty>
    <odeNavStructureProperty>
      <key>editableInPage</key>
      <value>false</value>
    </odeNavStructureProperty>
    <odeNavStructureProperty>
      <key>titlePage</key>
      <value>Justificación</value>
    </odeNavStructureProperty>
    <odeNavStructureProperty>
      <key>titleNode</key>
      <value></value>
    </odeNavStructureProperty>
    <odeNavStructureProperty>
      <key>titleHtml</key>
      <value></value>
    </odeNavStructureProperty>
    <odeNavStructureProperty>
      <key>description</key>
      <value></value>
    </odeNavStructureProperty>
  </odeNavStructureProperties>
  <odePagStructures>
    <odePagStructure>
      <odePageId>page-moc1wn8p-02z4ubxai</odePageId>
      <odeBlockId>20260423222439ZMIISJ</odeBlockId>
      <blockName>JUSTIFICACIÓN</blockName>
      <iconName></iconName>
      <odePagStructureOrder>1</odePagStructureOrder>
      <odePagStructureProperties>
        <odePagStructureProperty>
          <key>visibility</key>
          <value>true</value>
        </odePagStructureProperty>
        <odePagStructureProperty>
          <key>teacherOnly</key>
          <value>false</value>
        </odePagStructureProperty>
        <odePagStructureProperty>
          <key>allowToggle</key>
          <value>true</value>
        </odePagStructureProperty>
        <odePagStructureProperty>
          <key>minimized</key>
          <value>false</value>
        </odePagStructureProperty>
        <odePagStructureProperty>
          <key>cssClass</key>
          <value></value>
        </odePagStructureProperty>
      </odePagStructureProperties>
      <odeComponents>
        <odeComponent>
          <odePageId>page-moc1wn8p-02z4ubxai</odePageId>
          <odeBlockId>20260423222439ZMIISJ</odeBlockId>
          <odeIdeviceId>20260416214451941FOU</odeIdeviceId>
          <odeIdeviceTypeName>text</odeIdeviceTypeName>
          <htmlView><![CDATA[<div class="exe-text-template"><div class="textIdeviceContent">
            <div class="exe-text-activity">
                <div><p><img src="{{context_path}}/content/resources/20260416214451941FOU/mceclip6.png"></p><p class="clearfix"></p></div>
            </div></div></div>]]></htmlView>
          <jsonProperties><![CDATA[{"ideviceId":"20260416214451941FOU","textInfoDurationInput":"","textInfoDurationTextInput":"Duración","textInfoParticipantsInput":"","textInfoParticipantsTextInput":"Agrupamiento","textTextarea":"<p><img src=\"{{context_path}}/content/resources/20260416214451941FOU/mceclip6.png\" /></p>","textFeedbackInput":"Mostrar retroalimentación","textFeedbackTextarea":""}]]></jsonProperties>
          <odeComponentsOrder>1</odeComponentsOrder>
          <odeComponentsProperties>
            <odeComponentsProperty>
              <key>visibility</key>
              <value>true</value>
            </odeComponentsProperty>
            <odeComponentsProperty>
              <key>teacherOnly</key>
              <value>false</value>
            </odeComponentsProperty>
            <odeComponentsProperty>
              <key>cssClass</key>
              <value></value>
            </odeComponentsProperty>
          </odeComponentsProperties>
        </odeComponent>
      </odeComponents>
    </odePagStructure>
  </odePagStructures>
</odeNavStructure>
<odeNavStructure>
  <odePageId>page-moc1wn8q-a10qlxypr</odePageId>
  <odeParentPageId>page-moc1wn8f-dkkkxnpzw</odeParentPageId>
  <pageName>Secuencia</pageName>
  <odeNavStructureOrder>5</odeNavStructureOrder>
  <odeNavStructureProperties>
    <odeNavStructureProperty>
      <key>titlePage</key>
      <value>Secuencia</value>
    </odeNavStructureProperty>
    <odeNavStructureProperty>
      <key>visibility</key>
      <value>true</value>
    </odeNavStructureProperty>
    <odeNavStructureProperty>
      <key>highlight</key>
      <value>false</value>
    </odeNavStructureProperty>
    <odeNavStructureProperty>
      <key>hidePageTitle</key>
      <value>false</value>
    </odeNavStructureProperty>
    <odeNavStructureProperty>
      <key>editableInPage</key>
      <value>false</value>
    </odeNavStructureProperty>
    <odeNavStructureProperty>
      <key>titlePage</key>
      <value>Secuencia</value>
    </odeNavStructureProperty>
    <odeNavStructureProperty>
      <key>titleNode</key>
      <value></value>
    </odeNavStructureProperty>
    <odeNavStructureProperty>
      <key>titleHtml</key>
      <value></value>
    </odeNavStructureProperty>
    <odeNavStructureProperty>
      <key>description</key>
      <value></value>
    </odeNavStructureProperty>
  </odeNavStructureProperties>
  <odePagStructures>
    <odePagStructure>
      <odePageId>page-moc1wn8q-a10qlxypr</odePageId>
      <odeBlockId>20260423222439BRRFEG</odeBlockId>
      <blockName>Secuencia.</blockName>
      <iconName></iconName>
      <odePagStructureOrder>1</odePagStructureOrder>
      <odePagStructureProperties>
        <odePagStructureProperty>
          <key>visibility</key>
          <value>true</value>
        </odePagStructureProperty>
        <odePagStructureProperty>
          <key>teacherOnly</key>
          <value>false</value>
        </odePagStructureProperty>
        <odePagStructureProperty>
          <key>allowToggle</key>
          <value>true</value>
        </odePagStructureProperty>
        <odePagStructureProperty>
          <key>minimized</key>
          <value>false</value>
        </odePagStructureProperty>
        <odePagStructureProperty>
          <key>cssClass</key>
          <value></value>
        </odePagStructureProperty>
      </odePagStructureProperties>
      <odeComponents>
        <odeComponent>
          <odePageId>page-moc1wn8q-a10qlxypr</odePageId>
          <odeBlockId>20260423222439BRRFEG</odeBlockId>
          <odeIdeviceId>202604162150412402O5</odeIdeviceId>
          <odeIdeviceTypeName>text</odeIdeviceTypeName>
          <htmlView><![CDATA[<div class="exe-text-template"><div class="textIdeviceContent">
            <div class="exe-text-activity">
                <div><p><img src="{{context_path}}/content/resources/202604162150412402O5/mceclip5.png"></p>
<p></p>
<p><img src="{{context_path}}/content/resources/202604162150412402O5/mceclip6.png"></p><p class="clearfix"></p></div>
            </div></div></div>]]></htmlView>
          <jsonProperties><![CDATA[{"ideviceId":"202604162150412402O5","textInfoDurationInput":"","textInfoDurationTextInput":"Duración","textInfoParticipantsInput":"","textInfoParticipantsTextInput":"Agrupamiento","textTextarea":"<p><img src=\"{{context_path}}/content/resources/202604162150412402O5/mceclip5.png\" /></p>\n<p></p>\n<p><img src=\"{{context_path}}/content/resources/202604162150412402O5/mceclip6.png\" /></p>","textFeedbackInput":"Mostrar retroalimentación","textFeedbackTextarea":""}]]></jsonProperties>
          <odeComponentsOrder>1</odeComponentsOrder>
          <odeComponentsProperties>
            <odeComponentsProperty>
              <key>visibility</key>
              <value>true</value>
            </odeComponentsProperty>
            <odeComponentsProperty>
              <key>teacherOnly</key>
              <value>false</value>
            </odeComponentsProperty>
            <odeComponentsProperty>
              <key>cssClass</key>
              <value></value>
            </odeComponentsProperty>
          </odeComponentsProperties>
        </odeComponent>
      </odeComponents>
    </odePagStructure>
  </odePagStructures>
</odeNavStructure>
<odeNavStructure>
  <odePageId>page-moc1wn8q-1li67p7vb</odePageId>
  <odeParentPageId>page-moc1wn8f-dkkkxnpzw</odeParentPageId>
  <pageName>¿ Qué vamos a usar?</pageName>
  <odeNavStructureOrder>6</odeNavStructureOrder>
  <odeNavStructureProperties>
    <odeNavStructureProperty>
      <key>titlePage</key>
      <value>¿ Qué vamos a usar?</value>
    </odeNavStructureProperty>
    <odeNavStructureProperty>
      <key>visibility</key>
      <value>true</value>
    </odeNavStructureProperty>
    <odeNavStructureProperty>
      <key>highlight</key>
      <value>false</value>
    </odeNavStructureProperty>
    <odeNavStructureProperty>
      <key>hidePageTitle</key>
      <value>false</value>
    </odeNavStructureProperty>
    <odeNavStructureProperty>
      <key>editableInPage</key>
      <value>false</value>
    </odeNavStructureProperty>
    <odeNavStructureProperty>
      <key>titlePage</key>
      <value>¿ Qué vamos a usar?</value>
    </odeNavStructureProperty>
    <odeNavStructureProperty>
      <key>titleNode</key>
      <value></value>
    </odeNavStructureProperty>
    <odeNavStructureProperty>
      <key>titleHtml</key>
      <value></value>
    </odeNavStructureProperty>
    <odeNavStructureProperty>
      <key>description</key>
      <value></value>
    </odeNavStructureProperty>
  </odeNavStructureProperties>
  <odePagStructures>
    <odePagStructure>
      <odePageId>page-moc1wn8q-1li67p7vb</odePageId>
      <odeBlockId>20260423222439AGGBTT</odeBlockId>
      <blockName>Recursos del proyecto.</blockName>
      <iconName></iconName>
      <odePagStructureOrder>0</odePagStructureOrder>
      <odePagStructureProperties>
        <odePagStructureProperty>
          <key>visibility</key>
          <value>true</value>
        </odePagStructureProperty>
        <odePagStructureProperty>
          <key>teacherOnly</key>
          <value>false</value>
        </odePagStructureProperty>
        <odePagStructureProperty>
          <key>allowToggle</key>
          <value>true</value>
        </odePagStructureProperty>
        <odePagStructureProperty>
          <key>minimized</key>
          <value>false</value>
        </odePagStructureProperty>
        <odePagStructureProperty>
          <key>cssClass</key>
          <value></value>
        </odePagStructureProperty>
      </odePagStructureProperties>
      <odeComponents>
        <odeComponent>
          <odePageId>page-moc1wn8q-1li67p7vb</odePageId>
          <odeBlockId>20260423222439AGGBTT</odeBlockId>
          <odeIdeviceId>20260416215831873378</odeIdeviceId>
          <odeIdeviceTypeName>text</odeIdeviceTypeName>
          <htmlView><![CDATA[<div class="exe-text-template"><div class="textIdeviceContent">
            <div class="exe-text-activity">
                <div><p><img src="{{context_path}}/content/resources/20260416215831873378/mceclip7.png"></p><p class="clearfix"></p></div>
            </div></div></div>]]></htmlView>
          <jsonProperties><![CDATA[{"ideviceId":"20260416215831873378","textInfoDurationInput":"","textInfoDurationTextInput":"Duración","textInfoParticipantsInput":"","textInfoParticipantsTextInput":"Agrupamiento","textTextarea":"<p><img src=\"{{context_path}}/content/resources/20260416215831873378/mceclip7.png\" /></p>","textFeedbackInput":"Mostrar retroalimentación","textFeedbackTextarea":""}]]></jsonProperties>
          <odeComponentsOrder>1</odeComponentsOrder>
          <odeComponentsProperties>
            <odeComponentsProperty>
              <key>visibility</key>
              <value>true</value>
            </odeComponentsProperty>
            <odeComponentsProperty>
              <key>teacherOnly</key>
              <value>false</value>
            </odeComponentsProperty>
            <odeComponentsProperty>
              <key>cssClass</key>
              <value></value>
            </odeComponentsProperty>
          </odeComponentsProperties>
        </odeComponent>
      </odeComponents>
    </odePagStructure>
  </odePagStructures>
</odeNavStructure>
<odeNavStructure>
  <odePageId>page-moc1wn8r-0ybrxh1va</odePageId>
  <odeParentPageId>page-moc1wn8f-dkkkxnpzw</odeParentPageId>
  <pageName>¿ Cómo te evalúo?</pageName>
  <odeNavStructureOrder>7</odeNavStructureOrder>
  <odeNavStructureProperties>
    <odeNavStructureProperty>
      <key>titlePage</key>
      <value>¿ Cómo te evalúo?</value>
    </odeNavStructureProperty>
    <odeNavStructureProperty>
      <key>visibility</key>
      <value>true</value>
    </odeNavStructureProperty>
    <odeNavStructureProperty>
      <key>highlight</key>
      <value>false</value>
    </odeNavStructureProperty>
    <odeNavStructureProperty>
      <key>hidePageTitle</key>
      <value>false</value>
    </odeNavStructureProperty>
    <odeNavStructureProperty>
      <key>editableInPage</key>
      <value>false</value>
    </odeNavStructureProperty>
    <odeNavStructureProperty>
      <key>titlePage</key>
      <value>¿ Cómo te evalúo?</value>
    </odeNavStructureProperty>
    <odeNavStructureProperty>
      <key>titleNode</key>
      <value></value>
    </odeNavStructureProperty>
    <odeNavStructureProperty>
      <key>titleHtml</key>
      <value></value>
    </odeNavStructureProperty>
    <odeNavStructureProperty>
      <key>description</key>
      <value></value>
    </odeNavStructureProperty>
  </odeNavStructureProperties>
  <odePagStructures>
    <odePagStructure>
      <odePageId>page-moc1wn8r-0ybrxh1va</odePageId>
      <odeBlockId>20260423222439JKZPHZ</odeBlockId>
      <blockName>Evaluación.</blockName>
      <iconName></iconName>
      <odePagStructureOrder>1</odePagStructureOrder>
      <odePagStructureProperties>
        <odePagStructureProperty>
          <key>visibility</key>
          <value>true</value>
        </odePagStructureProperty>
        <odePagStructureProperty>
          <key>teacherOnly</key>
          <value>false</value>
        </odePagStructureProperty>
        <odePagStructureProperty>
          <key>allowToggle</key>
          <value>true</value>
        </odePagStructureProperty>
        <odePagStructureProperty>
          <key>minimized</key>
          <value>false</value>
        </odePagStructureProperty>
        <odePagStructureProperty>
          <key>cssClass</key>
          <value></value>
        </odePagStructureProperty>
      </odePagStructureProperties>
      <odeComponents>
        <odeComponent>
          <odePageId>page-moc1wn8r-0ybrxh1va</odePageId>
          <odeBlockId>20260423222439JKZPHZ</odeBlockId>
          <odeIdeviceId>202604162159111023AY</odeIdeviceId>
          <odeIdeviceTypeName>text</odeIdeviceTypeName>
          <htmlView><![CDATA[<div class="exe-text-template"><div class="textIdeviceContent">
            <div class="exe-text-activity">
                <div><p><br></p>
<p><br></p>
<p><img src="{{context_path}}/content/resources/202604162159111023AY/mceclip8.png"></p>
<p><br></p>
<p>&nbsp;&nbsp;</p>
<p><br></p>
<p><br></p>
<p><br></p><p class="clearfix"></p></div>
            </div></div></div>]]></htmlView>
          <jsonProperties><![CDATA[{"ideviceId":"202604162159111023AY","textInfoDurationInput":"","textInfoDurationTextInput":"Duración","textInfoParticipantsInput":"","textInfoParticipantsTextInput":"Agrupamiento","textTextarea":"<p><br /></p>\n<p><br /></p>\n<p><img src=\"{{context_path}}/content/resources/202604162159111023AY/mceclip8.png\" /></p>\n<p><br /></p>\n<p>  </p>\n<p><br /></p>\n<p><br /></p>\n<p><br /></p>","textFeedbackInput":"Mostrar retroalimentación","textFeedbackTextarea":""}]]></jsonProperties>
          <odeComponentsOrder>1</odeComponentsOrder>
          <odeComponentsProperties>
            <odeComponentsProperty>
              <key>visibility</key>
              <value>true</value>
            </odeComponentsProperty>
            <odeComponentsProperty>
              <key>teacherOnly</key>
              <value>false</value>
            </odeComponentsProperty>
            <odeComponentsProperty>
              <key>cssClass</key>
              <value></value>
            </odeComponentsProperty>
          </odeComponentsProperties>
        </odeComponent>
      </odeComponents>
    </odePagStructure>
  </odePagStructures>
</odeNavStructure>
<odeNavStructure>
  <odePageId>page-moc1wn8r-jsz123fvs</odePageId>
  <odeParentPageId>page-moc1wn8f-dkkkxnpzw</odeParentPageId>
  <pageName>Temporalización</pageName>
  <odeNavStructureOrder>8</odeNavStructureOrder>
  <odeNavStructureProperties>
    <odeNavStructureProperty>
      <key>titlePage</key>
      <value>Temporalización</value>
    </odeNavStructureProperty>
    <odeNavStructureProperty>
      <key>visibility</key>
      <value>true</value>
    </odeNavStructureProperty>
    <odeNavStructureProperty>
      <key>highlight</key>
      <value>false</value>
    </odeNavStructureProperty>
    <odeNavStructureProperty>
      <key>hidePageTitle</key>
      <value>false</value>
    </odeNavStructureProperty>
    <odeNavStructureProperty>
      <key>editableInPage</key>
      <value>false</value>
    </odeNavStructureProperty>
    <odeNavStructureProperty>
      <key>titlePage</key>
      <value>Temporalización</value>
    </odeNavStructureProperty>
    <odeNavStructureProperty>
      <key>titleNode</key>
      <value></value>
    </odeNavStructureProperty>
    <odeNavStructureProperty>
      <key>titleHtml</key>
      <value></value>
    </odeNavStructureProperty>
    <odeNavStructureProperty>
      <key>description</key>
      <value></value>
    </odeNavStructureProperty>
  </odeNavStructureProperties>
  <odePagStructures>
    <odePagStructure>
      <odePageId>page-moc1wn8r-jsz123fvs</odePageId>
      <odeBlockId>20260423222439SVYQHP</odeBlockId>
      <blockName>temporalización.</blockName>
      <iconName></iconName>
      <odePagStructureOrder>1</odePagStructureOrder>
      <odePagStructureProperties>
        <odePagStructureProperty>
          <key>visibility</key>
          <value>true</value>
        </odePagStructureProperty>
        <odePagStructureProperty>
          <key>teacherOnly</key>
          <value>false</value>
        </odePagStructureProperty>
        <odePagStructureProperty>
          <key>allowToggle</key>
          <value>true</value>
        </odePagStructureProperty>
        <odePagStructureProperty>
          <key>minimized</key>
          <value>false</value>
        </odePagStructureProperty>
        <odePagStructureProperty>
          <key>cssClass</key>
          <value></value>
        </odePagStructureProperty>
      </odePagStructureProperties>
      <odeComponents>
        <odeComponent>
          <odePageId>page-moc1wn8r-jsz123fvs</odePageId>
          <odeBlockId>20260423222439SVYQHP</odeBlockId>
          <odeIdeviceId>202604162207454797Z6</odeIdeviceId>
          <odeIdeviceTypeName>text</odeIdeviceTypeName>
          <htmlView><![CDATA[<div class="exe-text-template"><div class="textIdeviceContent">
            <div class="exe-text-activity">
                <div><p><img src="{{context_path}}/content/resources/202604162207454797Z6/mceclip9.png"></p><p class="clearfix"></p></div>
            </div></div></div>]]></htmlView>
          <jsonProperties><![CDATA[{"ideviceId":"202604162207454797Z6","textInfoDurationInput":"","textInfoDurationTextInput":"Duración","textInfoParticipantsInput":"","textInfoParticipantsTextInput":"Agrupamiento","textTextarea":"<p><img src=\"{{context_path}}/content/resources/202604162207454797Z6/mceclip9.png\" /></p>","textFeedbackInput":"Mostrar retroalimentación","textFeedbackTextarea":""}]]></jsonProperties>
          <odeComponentsOrder>1</odeComponentsOrder>
          <odeComponentsProperties>
            <odeComponentsProperty>
              <key>visibility</key>
              <value>true</value>
            </odeComponentsProperty>
            <odeComponentsProperty>
              <key>teacherOnly</key>
              <value>false</value>
            </odeComponentsProperty>
            <odeComponentsProperty>
              <key>cssClass</key>
              <value></value>
            </odeComponentsProperty>
          </odeComponentsProperties>
        </odeComponent>
      </odeComponents>
    </odePagStructure>
  </odePagStructures>
</odeNavStructure>
<odeNavStructure>
  <odePageId>page-moc1wn8s-d3won6pvs</odePageId>
  <odeParentPageId>page-moc1wn8f-dkkkxnpzw</odeParentPageId>
  <pageName>créditos</pageName>
  <odeNavStructureOrder>9</odeNavStructureOrder>
  <odeNavStructureProperties>
    <odeNavStructureProperty>
      <key>titlePage</key>
      <value>créditos</value>
    </odeNavStructureProperty>
    <odeNavStructureProperty>
      <key>visibility</key>
      <value>true</value>
    </odeNavStructureProperty>
    <odeNavStructureProperty>
      <key>highlight</key>
      <value>false</value>
    </odeNavStructureProperty>
    <odeNavStructureProperty>
      <key>hidePageTitle</key>
      <value>false</value>
    </odeNavStructureProperty>
    <odeNavStructureProperty>
      <key>editableInPage</key>
      <value>false</value>
    </odeNavStructureProperty>
    <odeNavStructureProperty>
      <key>titlePage</key>
      <value>créditos</value>
    </odeNavStructureProperty>
    <odeNavStructureProperty>
      <key>titleNode</key>
      <value>créditos</value>
    </odeNavStructureProperty>
    <odeNavStructureProperty>
      <key>titleHtml</key>
      <value></value>
    </odeNavStructureProperty>
    <odeNavStructureProperty>
      <key>description</key>
      <value></value>
    </odeNavStructureProperty>
  </odeNavStructureProperties>
  <odePagStructures>
    <odePagStructure>
      <odePageId>page-moc1wn8s-d3won6pvs</odePageId>
      <odeBlockId>20260423222439PELHPJ</odeBlockId>
      <blockName>créditos.</blockName>
      <iconName></iconName>
      <odePagStructureOrder>1</odePagStructureOrder>
      <odePagStructureProperties>
        <odePagStructureProperty>
          <key>visibility</key>
          <value>true</value>
        </odePagStructureProperty>
        <odePagStructureProperty>
          <key>teacherOnly</key>
          <value>false</value>
        </odePagStructureProperty>
        <odePagStructureProperty>
          <key>allowToggle</key>
          <value>true</value>
        </odePagStructureProperty>
        <odePagStructureProperty>
          <key>minimized</key>
          <value>false</value>
        </odePagStructureProperty>
        <odePagStructureProperty>
          <key>cssClass</key>
          <value></value>
        </odePagStructureProperty>
      </odePagStructureProperties>
      <odeComponents>
        <odeComponent>
          <odePageId>page-moc1wn8s-d3won6pvs</odePageId>
          <odeBlockId>20260423222439PELHPJ</odeBlockId>
          <odeIdeviceId>20260416221037446D4W</odeIdeviceId>
          <odeIdeviceTypeName>text</odeIdeviceTypeName>
          <htmlView><![CDATA[<div class="exe-text-template"><div class="textIdeviceContent">
            <div class="exe-text-activity">
                <div><p><img src="{{context_path}}/content/resources/20260416221037446D4W/mceclip14.png"></p><p class="clearfix"></p></div>
            </div></div></div>]]></htmlView>
          <jsonProperties><![CDATA[{"ideviceId":"20260416221037446D4W","textInfoDurationInput":"","textInfoDurationTextInput":"Duración","textInfoParticipantsInput":"","textInfoParticipantsTextInput":"Agrupamiento","textTextarea":"<p><img src=\"{{context_path}}/content/resources/20260416221037446D4W/mceclip14.png\" /></p>","textFeedbackInput":"Mostrar retroalimentación","textFeedbackTextarea":""}]]></jsonProperties>
          <odeComponentsOrder>1</odeComponentsOrder>
          <odeComponentsProperties>
            <odeComponentsProperty>
              <key>visibility</key>
              <value>true</value>
            </odeComponentsProperty>
            <odeComponentsProperty>
              <key>teacherOnly</key>
              <value>false</value>
            </odeComponentsProperty>
            <odeComponentsProperty>
              <key>cssClass</key>
              <value></value>
            </odeComponentsProperty>
          </odeComponentsProperties>
        </odeComponent>
      </odeComponents>
    </odePagStructure>
  </odePagStructures>
</odeNavStructure>
<odeNavStructure>
  <odePageId>page-moc1wn8t-tukcq4kie</odePageId>
  <odeParentPageId>page-moc1wn8f-dkkkxnpzw</odeParentPageId>
  <pageName>referencias</pageName>
  <odeNavStructureOrder>10</odeNavStructureOrder>
  <odeNavStructureProperties>
    <odeNavStructureProperty>
      <key>titlePage</key>
      <value>referencias</value>
    </odeNavStructureProperty>
    <odeNavStructureProperty>
      <key>visibility</key>
      <value>true</value>
    </odeNavStructureProperty>
    <odeNavStructureProperty>
      <key>highlight</key>
      <value>false</value>
    </odeNavStructureProperty>
    <odeNavStructureProperty>
      <key>hidePageTitle</key>
      <value>false</value>
    </odeNavStructureProperty>
    <odeNavStructureProperty>
      <key>editableInPage</key>
      <value>false</value>
    </odeNavStructureProperty>
    <odeNavStructureProperty>
      <key>titlePage</key>
      <value>referencias</value>
    </odeNavStructureProperty>
    <odeNavStructureProperty>
      <key>titleNode</key>
      <value>referencias</value>
    </odeNavStructureProperty>
    <odeNavStructureProperty>
      <key>titleHtml</key>
      <value></value>
    </odeNavStructureProperty>
    <odeNavStructureProperty>
      <key>description</key>
      <value></value>
    </odeNavStructureProperty>
  </odeNavStructureProperties>
  <odePagStructures>
    <odePagStructure>
      <odePageId>page-moc1wn8t-tukcq4kie</odePageId>
      <odeBlockId>20260423222439KDMSFX</odeBlockId>
      <blockName>referencias bibliográficas.</blockName>
      <iconName></iconName>
      <odePagStructureOrder>1</odePagStructureOrder>
      <odePagStructureProperties>
        <odePagStructureProperty>
          <key>visibility</key>
          <value>true</value>
        </odePagStructureProperty>
        <odePagStructureProperty>
          <key>teacherOnly</key>
          <value>false</value>
        </odePagStructureProperty>
        <odePagStructureProperty>
          <key>allowToggle</key>
          <value>true</value>
        </odePagStructureProperty>
        <odePagStructureProperty>
          <key>minimized</key>
          <value>false</value>
        </odePagStructureProperty>
        <odePagStructureProperty>
          <key>cssClass</key>
          <value></value>
        </odePagStructureProperty>
      </odePagStructureProperties>
      <odeComponents>
        <odeComponent>
          <odePageId>page-moc1wn8t-tukcq4kie</odePageId>
          <odeBlockId>20260423222439KDMSFX</odeBlockId>
          <odeIdeviceId>202604162223084880Z4</odeIdeviceId>
          <odeIdeviceTypeName>text</odeIdeviceTypeName>
          <htmlView><![CDATA[<div class="exe-text-template"><div class="textIdeviceContent">
            <div class="exe-text-activity">
                <div><p><img src="{{context_path}}/content/resources/202604162223084880Z4/mceclip15.png"></p><p class="clearfix"></p></div>
            </div></div></div>]]></htmlView>
          <jsonProperties><![CDATA[{"ideviceId":"202604162223084880Z4","textInfoDurationInput":"","textInfoDurationTextInput":"Duración","textInfoParticipantsInput":"","textInfoParticipantsTextInput":"Agrupamiento","textTextarea":"<p><img src=\"{{context_path}}/content/resources/202604162223084880Z4/mceclip15.png\" /></p>","textFeedbackInput":"Mostrar retroalimentación","textFeedbackTextarea":""}]]></jsonProperties>
          <odeComponentsOrder>1</odeComponentsOrder>
          <odeComponentsProperties>
            <odeComponentsProperty>
              <key>visibility</key>
              <value>true</value>
            </odeComponentsProperty>
            <odeComponentsProperty>
              <key>teacherOnly</key>
              <value>false</value>
            </odeComponentsProperty>
            <odeComponentsProperty>
              <key>cssClass</key>
              <value></value>
            </odeComponentsProperty>
          </odeComponentsProperties>
        </odeComponent>
      </odeComponents>
    </odePagStructure>
  </odePagStructures>
</odeNavStructure>
</odeNavStructures>
</ode>